kgtk/__init__.py
kgtk/__main__.py
kgtk/cli_argparse.py
kgtk/cli_entry.py
kgtk/configure_kgtk_notebooks.py
kgtk/dependencies.py
kgtk/exceptions.py
kgtk/files_config.py
kgtk/functions.py
kgtk/generator.py
kgtk/kgtkformat.py
kgtk/nomalizer.py
kgtk/cli/__dummy.py
kgtk/cli/__init__.py
kgtk/cli/__ticker.py
kgtk/cli/add_id.py
kgtk/cli/build-kgtk-search-input.py
kgtk/cli/calc.py
kgtk/cli/cat.py
kgtk/cli/clean_data.py
kgtk/cli/community-detection.py
kgtk/cli/compact.py
kgtk/cli/connected-components.py
kgtk/cli/convert-embeddings-format.py
kgtk/cli/count.py
kgtk/cli/expand.py
kgtk/cli/explode.py
kgtk/cli/export_gt.py
kgtk/cli/export_neo4j.py
kgtk/cli/export_wikidata.py
kgtk/cli/extract_wikidata_json.py
kgtk/cli/filter.py
kgtk/cli/generate_mediawiki_jsons.py
kgtk/cli/generate_wikidata_triples.py
kgtk/cli/graph_embeddings.py
kgtk/cli/graph_statistics.py
kgtk/cli/head.py
kgtk/cli/html.py
kgtk/cli/ifempty.py
kgtk/cli/ifexists.py
kgtk/cli/ifnotempty.py
kgtk/cli/ifnotexists.py
kgtk/cli/implode.py
kgtk/cli/import_atomic.py
kgtk/cli/import_concept_pairs.py
kgtk/cli/import_conceptnet.py
kgtk/cli/import_framenet.py
kgtk/cli/import_ntriples.py
kgtk/cli/import_visualgenome.py
kgtk/cli/import_wikidata.py
kgtk/cli/import_wordnet.py
kgtk/cli/join.py
kgtk/cli/lexicalize.py
kgtk/cli/lift.py
kgtk/cli/md.py
kgtk/cli/normalize.py
kgtk/cli/normalize_nodes.py
kgtk/cli/paths.py
kgtk/cli/query.py
kgtk/cli/reachable_nodes.py
kgtk/cli/remove_columns.py
kgtk/cli/rename_columns.py
kgtk/cli/reorder_columns.py
kgtk/cli/replace-nodes.py
kgtk/cli/sample.py
kgtk/cli/sort.py
kgtk/cli/split.py
kgtk/cli/table.py
kgtk/cli/tail.py
kgtk/cli/tee.py
kgtk/cli/text_embedding.py
kgtk/cli/unique.py
kgtk/cli/unreify_rdf_statements.py
kgtk/cli/unreify_values.py
kgtk/cli/validate-properties.py
kgtk/cli/validate.py
kgtk/cli/visualize-graph.py
kgtk/cli/zconcat.py
kgtk/exports/__init__.py
kgtk/exports/exportwikidata.py
kgtk/graph_analysis/__init__.py
kgtk/graph_analysis/community_detection.py
kgtk/graph_analysis/paths.py
kgtk-1.5.4.dist-info/LICENSE
kgtk-1.5.4.dist-info/METADATA
kgtk-1.5.4.dist-info/WHEEL
kgtk-1.5.4.dist-info/entry_points.txt
kgtk-1.5.4.dist-info/top_level.txt
kgtk-1.5.4.dist-info/RECORD
